{
  "Old Stove": {
    "textures": [
      "appliances_cooking_01_16",
      "appliances_cooking_01_17",
      "appliances_cooking_01_18",
      "appliances_cooking_01_19"
    ]
  },
  "Antique Stove": {
    "textures": [
      "appliances_cooking_01_16",
      "appliances_cooking_01_17",
      "appliances_cooking_01_18",
      "appliances_cooking_01_19"
    ]
  },
  "Wood Stove": {
    "textures": [
      "crafted_05_4",
      "crafted_05_5",
      "crafted_05_6",
      "crafted_05_7"
    ]
  },
  "Popsicle Fridge": {
    "textures": [
      "appliances_refrigeration_01_20",
      "appliances_refrigeration_01_21",
      "appliances_refrigeration_01_38",
      "appliances_refrigeration_01_39"
    ]
  },
  "Chest Freezer": {
    "textures": [
      "appliances_refrigeration_01_49",
      "appliances_refrigeration_01_48",
      "appliances_refrigeration_01_51",
      "appliances_refrigeration_01_50"
    ]
  },
  "Rain Collector Barrel": {
    "textures": [
      "carpentry_02_52",
      "carpentry_02_53",
      "carpentry_02_54",
      "carpentry_02_55",
      "carpentry_02_120",
      "carpentry_02_121",
      "carpentry_02_122",
      "carpentry_02_123",
      "carpentry_02_124",
      "carpentry_02_125",
      "carpentry_02_126",
      "carpentry_02_127"
    ]
  },
  "Water Dispenser": {
    "textures": [
      "location_business_office_generic_01_48",
      "location_business_office_generic_01_49",
      "location_business_office_generic_01_56",
      "location_business_office_generic_01_57"
    ]
  },
  "Well": {
    "textures": [
      "camping_01_16",
      "camping_01_67",
      "camping_01_66",
      "camping_01_65",
      "camping_01_64"
    ]
  },
  "Gun Locker": {
    "textures": [
      "furniture_storage_02_8",
      "furniture_storage_02_9",
      "furniture_storage_02_10",
      "furniture_storage_02_11",
      "location_military_generic_01_23",
      "location_military_generic_01_22",
      "location_military_generic_01_31",
      "location_military_generic_01_30"
    ]
  },
  "Generator": {
    "textures": [
      "appliances_misc_01_0",
      "appliances_misc_01_1",
      "appliances_misc_01_2",
      "appliances_misc_01_3",
      "appliances_misc_01_4",
      "appliances_misc_01_5",
      "appliances_misc_01_6",
      "appliances_misc_01_7",
      "appliances_misc_01_8",
      "appliances_misc_01_9",
      "appliances_misc_01_10",
      "appliances_misc_01_11",
      "appliances_misc_01_12",
      "appliances_misc_01_13",
      "appliances_misc_01_14",
      "appliances_misc_01_15"

    ]
  }
}
